LICENSE.txt
MANIFEST.in
README.md
setup.cfg
setup.py
picToPdf/__init__.py
picToPdf/picToPdf.pyd
picToPdf.egg-info/PKG-INFO
picToPdf.egg-info/SOURCES.txt
picToPdf.egg-info/dependency_links.txt
picToPdf.egg-info/top_level.txt
picToPdf/Function/__init__.py
picToPdf/Function/imgToPdf.pyd
picToPdf/Ui/PicToPdfUi.pyd
picToPdf/Ui/__init__.py